shipyard_googledrive/__init__.py
shipyard_googledrive/drive_utils.py
shipyard_googledrive/googledrive.py
shipyard_googledrive/cli/__init__.py
shipyard_googledrive/cli/authtest.py
shipyard_googledrive/cli/download.py
shipyard_googledrive/cli/upload.py
shipyard_gdrive-0.1.0.dist-info/METADATA
shipyard_gdrive-0.1.0.dist-info/WHEEL
shipyard_gdrive-0.1.0.dist-info/top_level.txt
shipyard_gdrive-0.1.0.dist-info/RECORD
